Metadata-Version: 1.0
Name: django-cronjobs
Version: 0.2.3
Summary: A simple Django app for running cron jobs.
Home-page: http://github.com/jsocol/django-cronjobs
Author: Mozilla
Author-email: james@mozilla.com
License: BSD
Platform: UNKNOWN
Classifier: Development Status :: 4 - Beta
Classifier: Environment :: Web Environment
Classifier: Environment :: Web Environment :: Mozilla
Classifier: Intended Audience :: Developers
Classifier: Framework :: Django
Classifier: License :: OSI Approved :: BSD License
Classifier: Operating System :: OS Independent
Classifier: Programming Language :: Python
Classifier: Topic :: Software Development :: Libraries :: Python Modules
